planetmint/README.md
planetmint/__init__.py
planetmint/abci/__init__.py
planetmint/abci/application_logic.py
planetmint/abci/block.py
planetmint/abci/parallel_validation.py
planetmint/abci/rpc.py
planetmint/abci/utils.py
planetmint/application/__init__.py
planetmint/application/basevalidationrules.py
planetmint/application/validator.py
planetmint/backend/README.md
planetmint/backend/__init__.py
planetmint/backend/connection.py
planetmint/backend/exceptions.py
planetmint/backend/localmongodb/__init__.py
planetmint/backend/localmongodb/connection.py
planetmint/backend/localmongodb/query.py
planetmint/backend/localmongodb/schema.py
planetmint/backend/models/__init__.py
planetmint/backend/models/asset.py
planetmint/backend/models/block.py
planetmint/backend/models/dbtransaction.py
planetmint/backend/models/fulfills.py
planetmint/backend/models/input.py
planetmint/backend/models/metadata.py
planetmint/backend/models/output.py
planetmint/backend/models/script.py
planetmint/backend/query.py
planetmint/backend/schema.py
planetmint/backend/tarantool/__init__.py
planetmint/backend/tarantool/const.py
planetmint/backend/tarantool/opt/init.lua
planetmint/backend/tarantool/sync_io/__init__.py
planetmint/backend/tarantool/sync_io/connection.py
planetmint/backend/tarantool/sync_io/query.py
planetmint/backend/tarantool/sync_io/schema.py
planetmint/backend/tarantool/tarantool.md
planetmint/backend/utils.py
planetmint/commands/__init__.py
planetmint/commands/election_types.py
planetmint/commands/planetmint.py
planetmint/commands/utils.py
planetmint/config.py
planetmint/config_utils.py
planetmint/const.py
planetmint/exceptions.py
planetmint/ipc/__init__.py
planetmint/ipc/events.py
planetmint/ipc/exchange.py
planetmint/model/__init__.py
planetmint/model/dataaccessor.py
planetmint/start.py
planetmint/utils/__init__.py
planetmint/utils/lazy.py
planetmint/utils/processes.py
planetmint/utils/python.py
planetmint/utils/singleton.py
planetmint/version.py
planetmint/web/__init__.py
planetmint-2.5.1.dist-info/LICENSE
planetmint-2.5.1.dist-info/METADATA
planetmint-2.5.1.dist-info/WHEEL
planetmint-2.5.1.dist-info/entry_points.txt
planetmint-2.5.1.dist-info/RECORD
