Metadata-Version: 2.1
Name: planetmint
Version: 2.5.1
Summary: Planetmint: The Blockchain Database
License: AGPLv3
Author: Planetmint contributors
Requires-Python: >=3.9,<4.0
Classifier: Development Status :: 4 - Beta
Classifier: Intended Audience :: Developers
Classifier: License :: OSI Approved :: Apache Software License
Classifier: License :: Other/Proprietary License
Classifier: Natural Language :: English
Classifier: Operating System :: MacOS :: MacOS X
Classifier: Operating System :: POSIX :: Linux
Classifier: Programming Language :: Python :: 3
Classifier: Programming Language :: Python :: 3.9
Classifier: Programming Language :: Python :: 3.10
Classifier: Programming Language :: Python :: 3.11
Classifier: Topic :: Database
Classifier: Topic :: Database :: Database Engines/Servers
Classifier: Topic :: Software Development
Requires-Dist: aiohttp (>=3.8.4,<4.0.0)
Requires-Dist: asynctnt (>=2.0.1,<3.0.0)
Requires-Dist: base58 (==2.1.1)
Requires-Dist: chardet (==3.0.4)
Requires-Dist: flask (==2.1.2)
Requires-Dist: flask-cors (==3.0.10)
Requires-Dist: flask-restful (==0.3.9)
Requires-Dist: gunicorn (==20.1.0)
Requires-Dist: jsonschema (==4.16.0)
Requires-Dist: logstats (==0.3.0)
Requires-Dist: nest-asyncio (==1.5.5)
Requires-Dist: packaging (>=22.0)
Requires-Dist: planetmint-abci (>=0.8.4,<0.9.0)
Requires-Dist: planetmint-ipld (>=0.0.3)
Requires-Dist: planetmint-transactions (>=0.8.1)
Requires-Dist: protobuf (==3.20.2)
Requires-Dist: pyasn1 (>=0.4.8)
Requires-Dist: pymongo (==3.11.4)
Requires-Dist: python-decouple (>=3.7,<4.0)
Requires-Dist: python-rapidjson (>=1.0)
Requires-Dist: pyyaml (==6.0.0)
Requires-Dist: requests (==2.31.0)
Requires-Dist: setproctitle (==1.2.2)
Requires-Dist: tarantool (>=0.12.1)
Requires-Dist: werkzeug (==2.0.3)
